README.md
setup.py
dj_pgnosql.egg-info/PKG-INFO
dj_pgnosql.egg-info/SOURCES.txt
dj_pgnosql.egg-info/dependency_links.txt
dj_pgnosql.egg-info/top_level.txt
example_project/__init__.py
example_project/settings.py
example_project/urls.py
example_project/wsgi.py
pgnosql/__init__.py
pgnosql/admin.py
pgnosql/apps.py
pgnosql/middleware.py
pgnosql/models.py
pgnosql/routers.py
pgnosql/tests.py
pgnosql/user.py
pgnosql/views.py
pgnosql/migrations/0001_initial.py
pgnosql/migrations/0002_auto_20190827_1950.py
pgnosql/migrations/__init__.py