Metadata-Version: 2.1
Name: dj-pgnosql
Version: 1.0.1
Home-page: https://gitlab.com/schoolorchestration/libs/dj-pgnosql
Author: Christo Crampton
Author-email: info@38.co.za
Classifier: Programming Language :: Python :: 3
Classifier: Operating System :: OS Independent
